MANIFEST.in
README.rst
setup.cfg
setup.py
docs/HISTORY.rst
docs/INSTALL.rst
docs/LICENSE.GPL
docs/LICENSE.txt
platocdp/__init__.py
platocdp.policy.egg-info/PKG-INFO
platocdp.policy.egg-info/SOURCES.txt
platocdp.policy.egg-info/dependency_links.txt
platocdp.policy.egg-info/entry_points.txt
platocdp.policy.egg-info/namespace_packages.txt
platocdp.policy.egg-info/not-zip-safe
platocdp.policy.egg-info/paster_plugins.txt
platocdp.policy.egg-info/requires.txt
platocdp.policy.egg-info/top_level.txt
platocdp/policy/__init__.py
platocdp/policy/configure.zcml
platocdp/policy/interfaces.py
platocdp/policy/patches.py
platocdp/policy/setuphandlers.py
platocdp/policy/locales/README.txt
platocdp/policy/overrides/__init__.py
platocdp/policy/overrides/admin.py
platocdp/policy/overrides/configure.zcml
platocdp/policy/overrides/logo.png
platocdp/policy/overrides/templates/plone-addsite.pt
platocdp/policy/profiles/default/browserlayer.xml
platocdp/policy/profiles/default/metadata.xml
platocdp/policy/profiles/default/platocdp.policy.marker.txt
platocdp/policy/upgrades/__init__.py
platocdp/policy/upgrades/handlers.py
platocdp/policy/upgrades/profiles.py