Metadata-Version: 1.1
Name: platocdp.policy
Version: 4.0b2
Summary: UNKNOWN
Home-page: http://github.com/koslab/
Author: KOSLAB Technologies
Author-email: izhar@kagesenshi.org
License: gpl
Platform: UNKNOWN
Classifier: Framework :: Plone
Classifier: Programming Language :: Python
Classifier: Topic :: Software Development :: Libraries :: Python Modules
